{
  "predictions": {
    "donde": {
      "colectivo": "para el Colectivo",
      "hospital": "queda el Hospital más cercano?",
      "comprar": "puedo comprar",
      "subte": "está el subte",
      "tren": "está el tren",
      "negocio": "hay un negocio",
      "pagar": "puedo pagar?"
    },
    "comprar": {
      "agua": "Agua",
      "comida": "Comida"
    },
    "ayuda": {
      "hospital": "tengo que ir a un hospital",
      "ambulancia": "necesito una ambulancia"
    },
    "hola": {
      "perdon": "te quería pedir Perdón"
    },
    "necesitar": {
      "hospital": "ir a un hospital"
    },
    "si": {
      "necesitar": "necesito",
      "saber": "se",
      "ir": "voy",
      "poder": "puedo"
    },
    "no": {
      "necesitar": "necesito",
      "saber": "se",
      "ir": "voy",
      "poder": "puedo"
    },
    "saber": {
      "que": "que es"
    },
    "muchas gracias": {
      "saludo": "chau"
    },
    "saludo": {
      "nombre": "mi nombre es"
    }
  },
  "replacements": {
    "necesitar": "necesito",
    "no entender": "No entendí, ¿puede repetir otra vez?",
    "cuando": "¿Cuándo es?",
    "dolor": "Siento Dolor",
    "duda": "Tengo una duda",
    "fiebre": "Tengo fiebre",
    "vomitar": "Tengo vómitos",
    "saludo": "Hola"
  },
  "sentences": {
    "si": "decisiones_model",
    "no": "decisiones_model",
    "saber": "saber_model",
    "comprar": "comprar_model",
    "necesitar": "necesitar_model",
    "ayuda": "ayuda_model",
    "colectivo": "numbers_model",
    "subte": "letters_model",
    "donde": "donde_model",
    "saludo": "saludo_model",
    "nombre": "letters_model"
  }
}